doc/sphinx/Makefile
doc/sphinx/advanced_UI.png
doc/sphinx/changelog.rst
doc/sphinx/conf.py
doc/sphinx/errata.rst
doc/sphinx/index.rst
doc/sphinx/installation.rst
doc/sphinx/modules.rst
doc/sphinx/requirements.txt
doc/sphinx/reverse_sphinx_path.py
doc/sphinx/simple_UI.png
doc/sphinx/usage.rst
doc/sphinx/_static/custom.css
doc/sphinx/modules/global_constants.rst
doc/sphinx/modules/hacks.rst
doc/sphinx/modules/index.rst
doc/sphinx/modules/main.rst
doc/sphinx/modules/telegram/api.rst
doc/sphinx/modules/telegram/codes.rst
doc/sphinx/modules/telegram/datatypes.rst
doc/sphinx/modules/telegram/index.rst
doc/sphinx/modules/telegram/parser.rst
doc/sphinx/modules/telegram/telegram.rst
doc/sphinx/modules/ui/advanced_tui.rst
doc/sphinx/modules/ui/command_line_ui.rst
doc/sphinx/modules/ui/control_interface.rst
doc/sphinx/modules/ui/index.rst
doc/sphinx/modules/ui/queuefile.rst
doc/sphinx/modules/ui/status_format.rst
doc/sphinx/modules/ui/table.rst
doc/sphinx/modules/ui/widgets.rst
doc/sphinx/modules/virtualpump/hardware_component.rst
doc/sphinx/modules/virtualpump/index.rst
doc/sphinx/modules/virtualpump/parameter_component.rst
doc/sphinx/modules/virtualpump/virtualconnection.rst
doc/sphinx/modules/virtualpump/virtualpump.rst
test_turboctl/__init__.py
test_turboctl/run_tests/run_tests.py
test_turboctl/run_tests/test_run_tests.py
test_turboctl/telegram/__init__.py
test_turboctl/telegram/test_api.py
test_turboctl/telegram/test_codes.py
test_turboctl/telegram/test_datatypes.py
test_turboctl/telegram/test_parser.py
test_turboctl/telegram/test_telegram.py
test_turboctl/telegram/.hypothesis/unicode_data/11.0.0/charmap.json.gz
test_turboctl/ui/__init.py__
test_turboctl/ui/test_abstractui.py
test_turboctl/ui/test_command_parser.py
test_turboctl/ui/test_correct_error_message.py
test_turboctl/ui/test_output.py
test_turboctl/ui/test_table.py
test_turboctl/ui/test_tui.py
test_turboctl/virtualpump/__init__.py
test_turboctl/virtualpump/test_hardware_component.py
turboctl-1.1.1.dist-info/METADATA
turboctl-1.1.1.dist-info/WHEEL
turboctl-1.1.1.dist-info/entry_points.txt
turboctl-1.1.1.dist-info/top_level.txt
turboctl-1.1.1.dist-info/RECORD
