Metadata-Version: 2.1
Name: turboctl
Version: 1.1.1
Summary: TurboCtl is a RS-232 controller for a Leybold TURBOVAC i or iX turbovacuum pump.
Author: Feliks Kivelä
License: GPL-3.0-or-later
Project-URL: homepage, https://github.com/fkivela/TurboCtl
Keywords: RS-232,Turbovac
Requires-Python: >=3.10
Requires-Dist: pyserial
Requires-Dist: tabulate
Provides-Extra: test
Requires-Dist: hypothesis ; extra == 'test'
Provides-Extra: urwid
Requires-Dist: urwid ; extra == 'urwid'
